setup.cfg
setup.py
miscprom/__init__.py
miscprom.egg-info/PKG-INFO
miscprom.egg-info/SOURCES.txt
miscprom.egg-info/dependency_links.txt
miscprom.egg-info/entry_points.txt
miscprom.egg-info/requires.txt
miscprom.egg-info/top_level.txt
miscprom/core/__init__.py
miscprom/core/admin.py
miscprom/core/apps.py
miscprom/core/models.py
miscprom/core/util.py
miscprom/core/views.py
miscprom/core/migrations/0001_initial.py
miscprom/core/migrations/__init__.py
miscprom/exporters/__init__.py
miscprom/exporters/currency.py
miscprom/exporters/rescuetime.py
miscprom/exporters/wanikani.py
miscprom/standalone/__init__.py
miscprom/standalone/manage.py
miscprom/standalone/settings.py
miscprom/standalone/urls.py
miscprom/standalone/wsgi.py