Metadata-Version: 2.1
Name: miscprom
Version: 0.0.1
Summary: Miscellaneous exporters
Home-page: https://github.com/kfdm/misc-exporters
Author: Paul Traylor
License: MIT License
Platform: UNKNOWN
Classifier: Environment :: Web Environment
Classifier: Framework :: Django
Classifier: Intended Audience :: Developers
Classifier: License :: OSI Approved :: MIT License
Classifier: Operating System :: OS Independent
Classifier: Programming Language :: Python :: 3.6
Classifier: Programming Language :: Python :: 3
Classifier: Programming Language :: Python
Classifier: Topic :: Internet :: WWW/HTTP :: Dynamic Content
Classifier: Topic :: Internet :: WWW/HTTP
Provides-Extra: postgres
Provides-Extra: dev
